zainpay/__init__.py
zainpay/utils/constants.py
zainpay/utils/api_client/client.py
zainpay/utils/api_client/factory.py
zainpay/virtual_account/zainbox.py
zainpay-0.0.0.dist-info/METADATA
zainpay-0.0.0.dist-info/WHEEL
zainpay-0.0.0.dist-info/top_level.txt
zainpay-0.0.0.dist-info/RECORD
